Metadata-Version: 1.1
Name: cerial
Version: 0.0.1
Summary: Python3 serializer with memoryview support
Home-page: https://github.com/vodik/cerial
Author: Simon Gomizelj
Author-email: simon@vodik.xyz
License: Apache 2
Platform: UNKNOWN
Classifier: Development Status :: 2 - Pre-Alpha
Classifier: Intended Audience :: Developers
Classifier: License :: OSI Approved :: BSD License
Classifier: Natural Language :: English
Classifier: Programming Language :: Python :: 3
Classifier: Programming Language :: Python :: 3.4
Classifier: Programming Language :: Python :: 3.5
Classifier: Programming Language :: Python :: 3.6
